{
	"credit": "Made with Blockbench",
	"textures": {
		"0": "mkweapons:items/iron_tool",
		"particle": "mkweapons:items/iron_tool"
	},
	"elements": [
		{
			"from": [7, 1, 7],
			"to": [9, 6, 9],
			"faces": {
				"north": {"uv": [12, 1, 15, 14], "texture": "#0"},
				"east": {"uv": [12, 1, 15, 14], "texture": "#0"},
				"south": {"uv": [12, 1, 15, 14], "texture": "#0"},
				"west": {"uv": [12, 1, 15, 14], "texture": "#0"},
				"up": {"uv": [9, 14, 11, 16], "texture": "#0"},
				"down": {"uv": [9, 0, 11, 2], "texture": "#0"}
			}
		},
		{
			"from": [7, 7, 7],
			"to": [9, 13, 9],
			"faces": {
				"north": {"uv": [9, 4, 10, 7], "texture": "#0"},
				"east": {"uv": [9, 5, 10, 8], "texture": "#0"},
				"south": {"uv": [10, 4, 11, 7], "texture": "#0"},
				"west": {"uv": [9, 10, 10, 13], "texture": "#0"},
				"up": {"uv": [9, 14, 11, 16], "texture": "#0"},
				"down": {"uv": [9, 0, 11, 2], "texture": "#0"}
			}
		},
		{
			"from": [6.5, 0, 6.5],
			"to": [9.5, 1, 9.5],
			"faces": {
				"north": {"uv": [6, 5, 9, 6], "texture": "#0"},
				"east": {"uv": [6, 7, 9, 8], "texture": "#0"},
				"south": {"uv": [6, 6, 9, 7], "texture": "#0"},
				"west": {"uv": [6, 5, 9, 6], "texture": "#0"},
				"up": {"uv": [6, 5, 9, 8], "texture": "#0"},
				"down": {"uv": [6, 6, 9, 9], "texture": "#0"}
			}
		},
		{
			"from": [6.5, 6, 6.5],
			"to": [9.5, 7, 9.5],
			"faces": {
				"north": {"uv": [6, 5, 9, 6], "texture": "#0"},
				"east": {"uv": [6, 7, 9, 8], "texture": "#0"},
				"south": {"uv": [6, 6, 9, 7], "texture": "#0"},
				"west": {"uv": [6, 5, 9, 6], "texture": "#0"},
				"up": {"uv": [6, 5, 9, 8], "texture": "#0"},
				"down": {"uv": [6, 6, 9, 9], "texture": "#0"}
			}
		},
		{
			"from": [6.5, 13, 6.5],
			"to": [9.5, 14, 9.5],
			"faces": {
				"north": {"uv": [6, 5, 9, 6], "texture": "#0"},
				"east": {"uv": [6, 7, 9, 8], "texture": "#0"},
				"south": {"uv": [6, 6, 9, 7], "texture": "#0"},
				"west": {"uv": [6, 5, 9, 6], "texture": "#0"},
				"up": {"uv": [6, 5, 9, 8], "texture": "#0"},
				"down": {"uv": [6, 6, 9, 9], "texture": "#0"}
			}
		},
		{
			"from": [4.5, 15, 6.5],
			"to": [11.5, 20, 9.5],
			"faces": {
				"north": {"uv": [1, 3, 6, 8], "texture": "#0"},
				"east": {"uv": [3, 5, 6, 9], "texture": "#0"},
				"south": {"uv": [0, 5, 5, 10], "texture": "#0"},
				"west": {"uv": [1, 2, 4, 7], "texture": "#0"},
				"up": {"uv": [1, 5, 4, 8], "texture": "#0"},
				"down": {"uv": [1, 6, 4, 9], "texture": "#0"}
			}
		},
		{
			"from": [6.5, 15, 4.5],
			"to": [9.5, 20, 6.5],
			"faces": {
				"north": {"uv": [1, 3, 4, 8], "texture": "#0"},
				"east": {"uv": [5, 5, 6, 10], "texture": "#0"},
				"south": {"uv": [0, 5, 3, 10], "texture": "#0"},
				"west": {"uv": [1, 2, 2, 7], "texture": "#0"},
				"up": {"uv": [1, 5, 4, 8], "texture": "#0"},
				"down": {"uv": [1, 6, 4, 9], "texture": "#0"}
			}
		},
		{
			"from": [6.5, 15, 9.5],
			"to": [9.5, 20, 11.5],
			"faces": {
				"north": {"uv": [1, 3, 4, 8], "texture": "#0"},
				"east": {"uv": [5, 5, 6, 10], "texture": "#0"},
				"south": {"uv": [0, 5, 3, 10], "texture": "#0"},
				"west": {"uv": [1, 2, 2, 7], "texture": "#0"},
				"up": {"uv": [1, 5, 4, 8], "texture": "#0"},
				"down": {"uv": [1, 6, 4, 9], "texture": "#0"}
			}
		},
		{
			"from": [6.5, 20, 6.5],
			"to": [9.5, 22, 9.5],
			"faces": {
				"north": {"uv": [1, 7, 4, 8], "texture": "#0"},
				"east": {"uv": [2, 12, 5, 13], "texture": "#0"},
				"south": {"uv": [0, 9, 3, 10], "texture": "#0"},
				"west": {"uv": [1, 6, 4, 7], "texture": "#0"},
				"up": {"uv": [1, 5, 4, 8], "texture": "#0"},
				"down": {"uv": [1, 6, 4, 9], "texture": "#0"}
			}
		},
		{
			"from": [6.5, 20, 5.5],
			"to": [9.5, 21, 6.5],
			"faces": {
				"north": {"uv": [1, 7, 4, 8], "texture": "#0"},
				"east": {"uv": [2, 12, 5, 13], "texture": "#0"},
				"south": {"uv": [0, 9, 3, 10], "texture": "#0"},
				"west": {"uv": [1, 6, 4, 7], "texture": "#0"},
				"up": {"uv": [1, 5, 4, 8], "texture": "#0"},
				"down": {"uv": [1, 6, 4, 9], "texture": "#0"}
			}
		},
		{
			"from": [6.5, 14, 5.5],
			"to": [9.5, 15, 6.5],
			"faces": {
				"north": {"uv": [1, 7, 4, 8], "texture": "#0"},
				"east": {"uv": [2, 12, 5, 13], "texture": "#0"},
				"south": {"uv": [0, 9, 3, 10], "texture": "#0"},
				"west": {"uv": [1, 6, 4, 7], "texture": "#0"},
				"up": {"uv": [1, 5, 4, 8], "texture": "#0"},
				"down": {"uv": [1, 6, 4, 9], "texture": "#0"}
			}
		},
		{
			"from": [6.5, 20, 9.5],
			"to": [9.5, 21, 10.5],
			"faces": {
				"north": {"uv": [1, 7, 4, 8], "texture": "#0"},
				"east": {"uv": [2, 12, 5, 13], "texture": "#0"},
				"south": {"uv": [0, 9, 3, 10], "texture": "#0"},
				"west": {"uv": [1, 6, 4, 7], "texture": "#0"},
				"up": {"uv": [1, 5, 4, 8], "texture": "#0"},
				"down": {"uv": [1, 6, 4, 9], "texture": "#0"}
			}
		},
		{
			"from": [6.5, 14, 9.5],
			"to": [9.5, 15, 10.5],
			"faces": {
				"north": {"uv": [1, 7, 4, 8], "texture": "#0"},
				"east": {"uv": [2, 12, 5, 13], "texture": "#0"},
				"south": {"uv": [0, 9, 3, 10], "texture": "#0"},
				"west": {"uv": [1, 6, 4, 7], "texture": "#0"},
				"up": {"uv": [1, 5, 4, 8], "texture": "#0"},
				"down": {"uv": [1, 6, 4, 9], "texture": "#0"}
			}
		},
		{
			"from": [9.5, 20, 6.5],
			"to": [10.5, 21, 9.5],
			"faces": {
				"north": {"uv": [2, 12, 5, 13], "texture": "#0"},
				"east": {"uv": [0, 9, 3, 10], "texture": "#0"},
				"south": {"uv": [1, 6, 4, 7], "texture": "#0"},
				"west": {"uv": [1, 7, 4, 8], "texture": "#0"},
				"up": {"uv": [1, 5, 4, 8], "rotation": 270, "texture": "#0"},
				"down": {"uv": [1, 6, 4, 9], "rotation": 90, "texture": "#0"}
			}
		},
		{
			"from": [9.5, 14, 6.5],
			"to": [10.5, 15, 9.5],
			"faces": {
				"north": {"uv": [2, 12, 5, 13], "texture": "#0"},
				"east": {"uv": [0, 9, 3, 10], "texture": "#0"},
				"south": {"uv": [1, 6, 4, 7], "texture": "#0"},
				"west": {"uv": [1, 7, 4, 8], "texture": "#0"},
				"up": {"uv": [1, 5, 4, 8], "rotation": 270, "texture": "#0"},
				"down": {"uv": [1, 6, 4, 9], "rotation": 90, "texture": "#0"}
			}
		},
		{
			"from": [5.5, 20, 6.5],
			"to": [6.5, 21, 9.5],
			"faces": {
				"north": {"uv": [2, 12, 5, 13], "texture": "#0"},
				"east": {"uv": [0, 9, 3, 10], "texture": "#0"},
				"south": {"uv": [1, 6, 4, 7], "texture": "#0"},
				"west": {"uv": [1, 7, 4, 8], "texture": "#0"},
				"up": {"uv": [1, 5, 4, 8], "rotation": 270, "texture": "#0"},
				"down": {"uv": [1, 6, 4, 9], "rotation": 90, "texture": "#0"}
			}
		},
		{
			"from": [5.5, 14, 6.5],
			"to": [6.5, 15, 9.5],
			"faces": {
				"north": {"uv": [2, 12, 5, 13], "texture": "#0"},
				"east": {"uv": [0, 9, 3, 10], "texture": "#0"},
				"south": {"uv": [1, 6, 4, 7], "texture": "#0"},
				"west": {"uv": [1, 7, 4, 8], "texture": "#0"},
				"up": {"uv": [1, 5, 4, 8], "rotation": 270, "texture": "#0"},
				"down": {"uv": [1, 6, 4, 9], "rotation": 90, "texture": "#0"}
			}
		}
	],
	"display": {
		"thirdperson_righthand": {
			"translation": [-0.5, 2.5, 1.5],
			"scale": [0.7, 0.97, 0.7]
		},
		"thirdperson_lefthand": {
			"translation": [-0.5, 2.5, 1.5],
			"scale": [0.7, 0.97, 0.7]
		},
		"firstperson_righthand": {
			"rotation": [-11, 26, -17],
			"translation": [-0.5, 0.75, 1.5],
			"scale": [0.51, 0.89, 0.5]
		},
		"firstperson_lefthand": {
			"rotation": [-11, 26, -17],
			"translation": [-0.5, 0.75, 1.5],
			"scale": [0.51, 0.89, 0.5]
		},
		"ground": {
			"rotation": [-11, -12, 63],
			"translation": [3, -0.75, 0.75],
			"scale": [0.51, 0.89, 0.5]
		},
		"gui": {
			"rotation": [30, 17, -38],
			"translation": [-1.75, -1.75, 1.5],
			"scale": [0.64, 0.86, 0.77]
		},
		"fixed": {
			"rotation": [0, 1, 42],
			"translation": [3, -2.5, 0],
			"scale": [1.34, 1, 1]
		}
	}
}